cli/__init__.py
cli/__main__.py
cli/_setup_cmds.py
cli/_version.py
cli/setup_hooks.py
cli/assets/__init__.py
cli/assets/favicon.svg
cli/commands/__init__.py
cli/commands/auth_main.py
cli/commands/cli_main.py
cli/commands/compose_main.py
cli/commands/plugin_main.py
cli/commands/protocol_main.py
cli/commands/queue_main.py
cli/commands/sync_main.py
cli/commands/term_main.py
cli/commands/user_main.py
cli/commands/vault_builder.py
cli/commands/vault_main.py
cli/commands/vscode_main.py
cli/commands/workflow_main.py
cli/config/__init__.py
cli/config/cli-config.json
cli/config/rediacc-gui-config.json
cli/config/rediacc-gui-translations.json
cli/config/rediacc-term-config.json
cli/core/__init__.py
cli/core/api_client.py
cli/core/config.py
cli/core/env_bootstrap.py
cli/core/env_config.py
cli/core/format_help.py
cli/core/help_generator.py
cli/core/linux_protocol_handler.py
cli/core/macos_protocol_handler.py
cli/core/msys2_installer.py
cli/core/protocol_handler.py
cli/core/repository_env.py
cli/core/shared.py
cli/core/telemetry.py
cli/gui/__init__.py
cli/gui/base.py
cli/gui/file_browser.py
cli/gui/login.py
cli/gui/main.py
cli/gui/system_status.py
cli/gui/utilities.py
rediacc-0.2.42.dist-info/licenses/LICENSE
rediacc-0.2.42.dist-info/METADATA
rediacc-0.2.42.dist-info/WHEEL
rediacc-0.2.42.dist-info/entry_points.txt
rediacc-0.2.42.dist-info/top_level.txt
rediacc-0.2.42.dist-info/RECORD
