Metadata-Version: 2.4
Name: rediacc
Version: 0.2.42
Summary: Infrastructure protection platform with 100-second recovery. Instant cloning, time-travel recovery, and 99.99% storage reduction for disaster prevention.
Author-email: Rediacc Team <info@rediacc.com>
Maintainer-email: Rediacc Team <info@rediacc.com>
License: MIT
Project-URL: Homepage, https://rediacc.com
Project-URL: Documentation, https://www.rediacc.com/docs
Project-URL: Repository, https://github.com/rediacc/cli
Project-URL: Bug Tracker, https://github.com/rediacc/cli/issues
Keywords: rediacc,disaster-recovery,backup,ai-safety,infrastructure-protection,ransomware-protection,time-travel-recovery,zero-cost-backup,devops,cloud-failover,database-cloning,snapshot,smart-deduplication
Classifier: Development Status :: 4 - Beta
Classifier: Intended Audience :: Developers
Classifier: Intended Audience :: System Administrators
Classifier: Topic :: Software Development :: Build Tools
Classifier: Topic :: System :: Systems Administration
Classifier: Topic :: Utilities
Classifier: Programming Language :: Python :: 3
Classifier: Programming Language :: Python :: 3.8
Classifier: Programming Language :: Python :: 3.9
Classifier: Programming Language :: Python :: 3.10
Classifier: Programming Language :: Python :: 3.11
Classifier: Programming Language :: Python :: 3.12
Classifier: Operating System :: OS Independent
Classifier: Operating System :: POSIX :: Linux
Classifier: Operating System :: MacOS
Classifier: Operating System :: Microsoft :: Windows
Classifier: Environment :: Console
Requires-Python: >=3.8
License-File: LICENSE
Requires-Dist: cryptography>=41.0.0
Requires-Dist: requests>=2.31.0
Requires-Dist: pyotp>=2.9.0
Provides-Extra: dev
Requires-Dist: pytest>=7.0; extra == "dev"
Requires-Dist: pytest-cov>=4.0; extra == "dev"
Requires-Dist: black>=23.0; extra == "dev"
Requires-Dist: flake8>=6.0; extra == "dev"
Requires-Dist: mypy>=1.0; extra == "dev"
Requires-Dist: build>=0.10; extra == "dev"
Requires-Dist: twine>=4.0; extra == "dev"
Provides-Extra: test
Requires-Dist: pytest>=7.0; extra == "test"
Requires-Dist: pytest-cov>=4.0; extra == "test"
Requires-Dist: pyyaml>=6.0; extra == "test"
Requires-Dist: playwright>=1.40.0; extra == "test"
Requires-Dist: mss>=9.0.0; extra == "test"
Dynamic: license-file
